[
  {
    "filename": "mediation1.pdf",
    "page": 3
  },
  {
    "filename": "mediation1.pdf",
    "page": 4
  },
  {
    "filename": "mediation1.pdf",
    "page": 5
  },
  {
    "filename": "mediation1.pdf",
    "page": 6
  },
  {
    "filename": "mediation1.pdf",
    "page": 7
  },
  {
    "filename": "mediation1.pdf",
    "page": 8
  },
  {
    "filename": "mediation1.pdf",
    "page": 9
  },
  {
    "filename": "mediation1.pdf",
    "page": 10
  },
  {
    "filename": "mediation1.pdf",
    "page": 11
  },
  {
    "filename": "mediation1.pdf",
    "page": 12
  },
  {
    "filename": "mediation1.pdf",
    "page": 13
  },
  {
    "filename": "mediation1.pdf",
    "page": 14
  },
  {
    "filename": "mediation1.pdf",
    "page": 15
  },
  {
    "filename": "mediation1.pdf",
    "page": 16
  },
  {
    "filename": "mediation1.pdf",
    "page": 17
  },
  {
    "filename": "mediation1.pdf",
    "page": 18
  },
  {
    "filename": "mediation1.pdf",
    "page": 19
  },
  {
    "filename": "mediation1.pdf",
    "page": 20
  },
  {
    "filename": "mediation1.pdf",
    "page": 21
  },
  {
    "filename": "mediation1.pdf",
    "page": 22
  },
  {
    "filename": "mediation1.pdf",
    "page": 23
  },
  {
    "filename": "mediation1.pdf",
    "page": 24
  },
  {
    "filename": "mediation1.pdf",
    "page": 25
  },
  {
    "filename": "mediation1.pdf",
    "page": 26
  },
  {
    "filename": "mediation1.pdf",
    "page": 27
  },
  {
    "filename": "mediation1.pdf",
    "page": 28
  },
  {
    "filename": "mediation1.pdf",
    "page": 29
  },
  {
    "filename": "mediation1.pdf",
    "page": 30
  },
  {
    "filename": "mediation1.pdf",
    "page": 31
  },
  {
    "filename": "mediation1.pdf",
    "page": 32
  },
  {
    "filename": "mediation1.pdf",
    "page": 33
  },
  {
    "filename": "mediation1.pdf",
    "page": 34
  },
  {
    "filename": "mediation1.pdf",
    "page": 35
  },
  {
    "filename": "mediation1.pdf",
    "page": 36
  },
  {
    "filename": "mediation1.pdf",
    "page": 37
  },
  {
    "filename": "mediation1.pdf",
    "page": 38
  },
  {
    "filename": "mediation1.pdf",
    "page": 39
  },
  {
    "filename": "mediation1.pdf",
    "page": 40
  },
  {
    "filename": "mediation1.pdf",
    "page": 41
  },
  {
    "filename": "mediation1.pdf",
    "page": 42
  },
  {
    "filename": "mediation1.pdf",
    "page": 43
  },
  {
    "filename": "mediation1.pdf",
    "page": 44
  },
  {
    "filename": "mediation1.pdf",
    "page": 45
  },
  {
    "filename": "mediation1.pdf",
    "page": 46
  },
  {
    "filename": "mediation1.pdf",
    "page": 47
  },
  {
    "filename": "mediation1.pdf",
    "page": 48
  },
  {
    "filename": "mediation1.pdf",
    "page": 49
  },
  {
    "filename": "mediation1.pdf",
    "page": 50
  },
  {
    "filename": "mediation1.pdf",
    "page": 51
  },
  {
    "filename": "mediation1.pdf",
    "page": 52
  },
  {
    "filename": "mediation1.pdf",
    "page": 53
  },
  {
    "filename": "mediation1.pdf",
    "page": 54
  },
  {
    "filename": "mediation1.pdf",
    "page": 55
  },
  {
    "filename": "mediation1.pdf",
    "page": 56
  },
  {
    "filename": "mediation1.pdf",
    "page": 57
  },
  {
    "filename": "mediation1.pdf",
    "page": 58
  },
  {
    "filename": "mediation1.pdf",
    "page": 59
  },
  {
    "filename": "mediation1.pdf",
    "page": 60
  },
  {
    "filename": "mediation1.pdf",
    "page": 61
  },
  {
    "filename": "mediation1.pdf",
    "page": 62
  },
  {
    "filename": "mediation1.pdf",
    "page": 63
  },
  {
    "filename": "mediation1.pdf",
    "page": 64
  },
  {
    "filename": "mediation1.pdf",
    "page": 65
  },
  {
    "filename": "mediation1.pdf",
    "page": 66
  },
  {
    "filename": "mediation1.pdf",
    "page": 67
  },
  {
    "filename": "mediation1.pdf",
    "page": 68
  },
  {
    "filename": "mediation1.pdf",
    "page": 69
  },
  {
    "filename": "mediation1.pdf",
    "page": 70
  },
  {
    "filename": "mediation1.pdf",
    "page": 71
  },
  {
    "filename": "mediation1.pdf",
    "page": 72
  },
  {
    "filename": "mediation1.pdf",
    "page": 73
  },
  {
    "filename": "mediation1.pdf",
    "page": 74
  },
  {
    "filename": "mediation1.pdf",
    "page": 75
  },
  {
    "filename": "mediation1.pdf",
    "page": 76
  },
  {
    "filename": "mediation1.pdf",
    "page": 77
  },
  {
    "filename": "mediation1.pdf",
    "page": 78
  },
  {
    "filename": "mediation1.pdf",
    "page": 79
  },
  {
    "filename": "mediation1.pdf",
    "page": 80
  },
  {
    "filename": "mediation1.pdf",
    "page": 81
  },
  {
    "filename": "mediation1.pdf",
    "page": 82
  },
  {
    "filename": "mediation1.pdf",
    "page": 83
  },
  {
    "filename": "mediation1.pdf",
    "page": 84
  },
  {
    "filename": "mediation1.pdf",
    "page": 85
  },
  {
    "filename": "mediation1.pdf",
    "page": 86
  },
  {
    "filename": "mediation1.pdf",
    "page": 87
  },
  {
    "filename": "mediation1.pdf",
    "page": 88
  },
  {
    "filename": "mediation1.pdf",
    "page": 89
  },
  {
    "filename": "mediation1.pdf",
    "page": 90
  },
  {
    "filename": "mediation1.pdf",
    "page": 91
  },
  {
    "filename": "mediation1.pdf",
    "page": 92
  },
  {
    "filename": "mediation1.pdf",
    "page": 93
  },
  {
    "filename": "mediation1.pdf",
    "page": 94
  },
  {
    "filename": "mediation1.pdf",
    "page": 95
  },
  {
    "filename": "mediation1.pdf",
    "page": 96
  },
  {
    "filename": "mediation1.pdf",
    "page": 97
  },
  {
    "filename": "mediation1.pdf",
    "page": 98
  },
  {
    "filename": "mediation1.pdf",
    "page": 99
  },
  {
    "filename": "mediation1.pdf",
    "page": 100
  },
  {
    "filename": "mediation1.pdf",
    "page": 101
  },
  {
    "filename": "mediation1.pdf",
    "page": 102
  },
  {
    "filename": "mediation1.pdf",
    "page": 103
  },
  {
    "filename": "mediation1.pdf",
    "page": 104
  },
  {
    "filename": "mediation1.pdf",
    "page": 105
  },
  {
    "filename": "mediation1.pdf",
    "page": 106
  },
  {
    "filename": "mediation1.pdf",
    "page": 107
  },
  {
    "filename": "mediation1.pdf",
    "page": 108
  },
  {
    "filename": "mediation1.pdf",
    "page": 109
  },
  {
    "filename": "mediation1.pdf",
    "page": 110
  },
  {
    "filename": "mediation1.pdf",
    "page": 111
  },
  {
    "filename": "mediation1.pdf",
    "page": 112
  },
  {
    "filename": "mediation1.pdf",
    "page": 113
  },
  {
    "filename": "mediation1.pdf",
    "page": 114
  },
  {
    "filename": "mediation1.pdf",
    "page": 115
  },
  {
    "filename": "mediation1.pdf",
    "page": 116
  },
  {
    "filename": "mediation1.pdf",
    "page": 117
  },
  {
    "filename": "mediation1.pdf",
    "page": 118
  },
  {
    "filename": "mediation1.pdf",
    "page": 119
  },
  {
    "filename": "mediation1.pdf",
    "page": 120
  },
  {
    "filename": "mediation1.pdf",
    "page": 121
  },
  {
    "filename": "mediation1.pdf",
    "page": 122
  },
  {
    "filename": "mediation1.pdf",
    "page": 123
  },
  {
    "filename": "mediation1.pdf",
    "page": 124
  },
  {
    "filename": "mediation1.pdf",
    "page": 125
  },
  {
    "filename": "mediation1.pdf",
    "page": 126
  },
  {
    "filename": "mediation1.pdf",
    "page": 127
  },
  {
    "filename": "mediation1.pdf",
    "page": 128
  },
  {
    "filename": "mediation1.pdf",
    "page": 129
  },
  {
    "filename": "mediation1.pdf",
    "page": 130
  },
  {
    "filename": "mediation1.pdf",
    "page": 131
  },
  {
    "filename": "mediation1.pdf",
    "page": 132
  },
  {
    "filename": "mediation1.pdf",
    "page": 133
  },
  {
    "filename": "mediation1.pdf",
    "page": 134
  },
  {
    "filename": "mediation1.pdf",
    "page": 135
  },
  {
    "filename": "mediation1.pdf",
    "page": 136
  },
  {
    "filename": "mediation1.pdf",
    "page": 137
  },
  {
    "filename": "mediation1.pdf",
    "page": 138
  },
  {
    "filename": "mediation1.pdf",
    "page": 139
  },
  {
    "filename": "mediation1.pdf",
    "page": 140
  },
  {
    "filename": "mediation1.pdf",
    "page": 141
  },
  {
    "filename": "mediation1.pdf",
    "page": 142
  },
  {
    "filename": "mediation1.pdf",
    "page": 143
  },
  {
    "filename": "mediation1.pdf",
    "page": 144
  },
  {
    "filename": "mediation1.pdf",
    "page": 145
  },
  {
    "filename": "mediation1.pdf",
    "page": 146
  },
  {
    "filename": "mediation1.pdf",
    "page": 147
  },
  {
    "filename": "mediation1.pdf",
    "page": 148
  },
  {
    "filename": "mediation1.pdf",
    "page": 149
  },
  {
    "filename": "mediation1.pdf",
    "page": 150
  },
  {
    "filename": "mediation1.pdf",
    "page": 151
  },
  {
    "filename": "mediation1.pdf",
    "page": 152
  },
  {
    "filename": "mediation1.pdf",
    "page": 153
  },
  {
    "filename": "mediation1.pdf",
    "page": 154
  },
  {
    "filename": "mediation1.pdf",
    "page": 155
  },
  {
    "filename": "mediation1.pdf",
    "page": 156
  },
  {
    "filename": "mediation1.pdf",
    "page": 157
  },
  {
    "filename": "mediation1.pdf",
    "page": 158
  },
  {
    "filename": "mediation1.pdf",
    "page": 159
  },
  {
    "filename": "mediation1.pdf",
    "page": 160
  },
  {
    "filename": "mediation1.pdf",
    "page": 161
  },
  {
    "filename": "mediation1.pdf",
    "page": 162
  },
  {
    "filename": "mediation1.pdf",
    "page": 163
  },
  {
    "filename": "mediation1.pdf",
    "page": 164
  },
  {
    "filename": "mediation1.pdf",
    "page": 165
  },
  {
    "filename": "mediation1.pdf",
    "page": 166
  },
  {
    "filename": "mediation1.pdf",
    "page": 167
  },
  {
    "filename": "mediation1.pdf",
    "page": 168
  },
  {
    "filename": "mediation1.pdf",
    "page": 169
  },
  {
    "filename": "mediation1.pdf",
    "page": 170
  },
  {
    "filename": "mediation1.pdf",
    "page": 171
  },
  {
    "filename": "mediation1.pdf",
    "page": 172
  },
  {
    "filename": "mediation1.pdf",
    "page": 173
  },
  {
    "filename": "mediation1.pdf",
    "page": 174
  },
  {
    "filename": "mediation1.pdf",
    "page": 175
  },
  {
    "filename": "mediation1.pdf",
    "page": 176
  },
  {
    "filename": "mediation1.pdf",
    "page": 177
  },
  {
    "filename": "mediation1.pdf",
    "page": 178
  },
  {
    "filename": "mediation1.pdf",
    "page": 179
  },
  {
    "filename": "mediation1.pdf",
    "page": 180
  },
  {
    "filename": "mediation1.pdf",
    "page": 181
  },
  {
    "filename": "mediation1.pdf",
    "page": 182
  },
  {
    "filename": "mediation1.pdf",
    "page": 183
  },
  {
    "filename": "mediation1.pdf",
    "page": 184
  },
  {
    "filename": "mediation2.pdf",
    "page": 4
  },
  {
    "filename": "mediation2.pdf",
    "page": 5
  },
  {
    "filename": "mediation2.pdf",
    "page": 9
  },
  {
    "filename": "mediation2.pdf",
    "page": 10
  },
  {
    "filename": "mediation2.pdf",
    "page": 12
  },
  {
    "filename": "mediation2.pdf",
    "page": 14
  },
  {
    "filename": "mediation2.pdf",
    "page": 15
  },
  {
    "filename": "mediation2.pdf",
    "page": 16
  },
  {
    "filename": "mediation2.pdf",
    "page": 17
  },
  {
    "filename": "mediation2.pdf",
    "page": 18
  },
  {
    "filename": "mediation2.pdf",
    "page": 19
  },
  {
    "filename": "mediation2.pdf",
    "page": 20
  },
  {
    "filename": "mediation2.pdf",
    "page": 21
  },
  {
    "filename": "mediation2.pdf",
    "page": 22
  },
  {
    "filename": "mediation2.pdf",
    "page": 23
  },
  {
    "filename": "mediation2.pdf",
    "page": 24
  },
  {
    "filename": "mediation2.pdf",
    "page": 25
  },
  {
    "filename": "mediation2.pdf",
    "page": 26
  },
  {
    "filename": "mediation2.pdf",
    "page": 27
  },
  {
    "filename": "mediation2.pdf",
    "page": 28
  },
  {
    "filename": "mediation2.pdf",
    "page": 29
  },
  {
    "filename": "mediation2.pdf",
    "page": 30
  },
  {
    "filename": "mediation2.pdf",
    "page": 31
  },
  {
    "filename": "mediation2.pdf",
    "page": 32
  },
  {
    "filename": "mediation2.pdf",
    "page": 33
  },
  {
    "filename": "mediation2.pdf",
    "page": 34
  },
  {
    "filename": "mediation2.pdf",
    "page": 35
  },
  {
    "filename": "mediation2.pdf",
    "page": 36
  },
  {
    "filename": "mediation2.pdf",
    "page": 37
  },
  {
    "filename": "mediation2.pdf",
    "page": 38
  },
  {
    "filename": "mediation2.pdf",
    "page": 39
  },
  {
    "filename": "mediation2.pdf",
    "page": 40
  },
  {
    "filename": "mediation2.pdf",
    "page": 41
  },
  {
    "filename": "mediation2.pdf",
    "page": 42
  },
  {
    "filename": "mediation2.pdf",
    "page": 43
  },
  {
    "filename": "mediation2.pdf",
    "page": 44
  },
  {
    "filename": "mediation2.pdf",
    "page": 45
  },
  {
    "filename": "mediation2.pdf",
    "page": 46
  },
  {
    "filename": "mediation2.pdf",
    "page": 47
  },
  {
    "filename": "mediation2.pdf",
    "page": 48
  },
  {
    "filename": "mediation2.pdf",
    "page": 49
  },
  {
    "filename": "mediation2.pdf",
    "page": 50
  },
  {
    "filename": "mediation2.pdf",
    "page": 51
  },
  {
    "filename": "mediation2.pdf",
    "page": 52
  },
  {
    "filename": "mediation2.pdf",
    "page": 53
  },
  {
    "filename": "mediation2.pdf",
    "page": 54
  },
  {
    "filename": "mediation2.pdf",
    "page": 55
  },
  {
    "filename": "mediation2.pdf",
    "page": 56
  },
  {
    "filename": "mediation2.pdf",
    "page": 57
  },
  {
    "filename": "mediation2.pdf",
    "page": 58
  },
  {
    "filename": "mediation2.pdf",
    "page": 59
  },
  {
    "filename": "mediation2.pdf",
    "page": 60
  },
  {
    "filename": "mediation3.pdf",
    "page": 1
  },
  {
    "filename": "mediation3.pdf",
    "page": 2
  },
  {
    "filename": "mediation3.pdf",
    "page": 3
  },
  {
    "filename": "mediation3.pdf",
    "page": 4
  },
  {
    "filename": "mediation3.pdf",
    "page": 5
  },
  {
    "filename": "mediation3.pdf",
    "page": 6
  },
  {
    "filename": "mediation3.pdf",
    "page": 7
  },
  {
    "filename": "mediation3.pdf",
    "page": 8
  },
  {
    "filename": "mediation3.pdf",
    "page": 9
  },
  {
    "filename": "mediation3.pdf",
    "page": 10
  },
  {
    "filename": "mediation3.pdf",
    "page": 11
  },
  {
    "filename": "mediation3.pdf",
    "page": 12
  },
  {
    "filename": "mediation3.pdf",
    "page": 13
  },
  {
    "filename": "mediation3.pdf",
    "page": 14
  },
  {
    "filename": "mediation3.pdf",
    "page": 15
  },
  {
    "filename": "mediation3.pdf",
    "page": 16
  },
  {
    "filename": "mediation3.pdf",
    "page": 17
  },
  {
    "filename": "mediation3.pdf",
    "page": 18
  },
  {
    "filename": "mediation3.pdf",
    "page": 19
  },
  {
    "filename": "mediation3.pdf",
    "page": 20
  },
  {
    "filename": "mediation3.pdf",
    "page": 21
  },
  {
    "filename": "mediation3.pdf",
    "page": 22
  },
  {
    "filename": "mediation3.pdf",
    "page": 23
  },
  {
    "filename": "mediation3.pdf",
    "page": 24
  },
  {
    "filename": "mediation3.pdf",
    "page": 25
  },
  {
    "filename": "mediation3.pdf",
    "page": 26
  },
  {
    "filename": "mediation3.pdf",
    "page": 27
  },
  {
    "filename": "mediation3.pdf",
    "page": 28
  },
  {
    "filename": "mediation3.pdf",
    "page": 29
  },
  {
    "filename": "mediation3.pdf",
    "page": 30
  },
  {
    "filename": "mediation3.pdf",
    "page": 32
  },
  {
    "filename": "mediation3.pdf",
    "page": 33
  },
  {
    "filename": "mediation3.pdf",
    "page": 34
  }
]